snowflake/demos/__init__.py
snowflake/demos/_constants.py
snowflake/demos/_demo_connection.py
snowflake/demos/_demo_handle.py
snowflake/demos/_demos_loader.py
snowflake/demos/_environment_detection.py
snowflake/demos/_lib.py
snowflake/demos/_logging.py
snowflake/demos/_progress_wrapper.py
snowflake/demos/_telemetry.py
snowflake/demos/_utils.py
snowflake/demos/version.py
snowflake/demos/data/analysis-churn-notebooks/notebooks/0_start_here.ipynb
snowflake/demos/data/analysis-churn-notebooks/notebooks/1_telco_churn_ml_feature_engineering.ipynb
snowflake/demos/data/analysis-churn-notebooks/notebooks/environment.yml
snowflake/demos/data/analysis-churn-notebooks/scripts/setup.sql
snowflake/demos/data/analysis-churn-notebooks/scripts/teardown.sql
snowflake/demos/data/get-started-partitioned-models/notebooks/0_start_here.ipynb
snowflake/demos/data/get-started-partitioned-models/notebooks/environment.yml
snowflake/demos/data/get-started-partitioned-models/scripts/setup.sql
snowflake/demos/data/get-started-snowflake-ml/notebooks/0_start_here.ipynb
snowflake/demos/data/get-started-snowflake-ml/notebooks/1_sf_nb_snowflake_ml_feature_transformations.ipynb
snowflake/demos/data/get-started-snowflake-ml/notebooks/2_sf_nb_snowflake_ml_model_training_inference.ipynb
snowflake/demos/data/get-started-snowflake-ml/notebooks/3_sf_nb_snowpark_ml_adv_mlops.ipynb
snowflake/demos/data/get-started-snowflake-ml/notebooks/environment.yml
snowflake/demos/data/get-started-snowflake-ml/scripts/setup.sql
snowflake/demos/data/get-started-snowflake-ml/scripts/teardown.sql
snowflake/demos/data/get-started-snowpark-ws-nb/notebooks/0_start_here.ipynb
snowflake/demos/data/get-started-snowpark-ws-nb/scripts/setup.sql
snowflake/demos/data/intro-to-feature-store-nb/notebooks/0_start_here.ipynb
snowflake/demos/data/intro-to-feature-store-nb/notebooks/environment.yml
snowflake/demos/data/intro-to-feature-store-nb/scripts/setup.sql
snowflake/demos/resources/demo-mappings.csv
snowflake_demos-0.1.4.dist-info/METADATA
snowflake_demos-0.1.4.dist-info/WHEEL
snowflake_demos-0.1.4.dist-info/RECORD
